{
  "project_info": {
    "project_number": "64637743473",
    "project_id": "ecommerce-24bac",
    "storage_bucket": "ecommerce-24bac.appspot.com"
  },
  "client": [
    {
      "client_info": {
        "mobilesdk_app_id": "1:64637743473:android:b23d4081a984316ea9c6d0",
        "android_client_info": {
          "package_name": "com.khanish.shopease"
        }
      },
      "oauth_client": [],
      "api_key": [
        {
          "current_key": "AIzaSyA4FF-IH-XhHnLShwkDZ8V_0_Joj_x7fWY"
        }
      ],
      "services": {
        "appinvite_service": {
          "other_platform_oauth_client": []
        }
      }
    }
  ],
  "configuration_version": "1"
}